fauxioapi/__init__.py
fauxioapi/fauxioapi.py
fauxioapi-0.1.5.dist-info/DESCRIPTION.rst
fauxioapi-0.1.5.dist-info/METADATA
fauxioapi-0.1.5.dist-info/RECORD
fauxioapi-0.1.5.dist-info/WHEEL
fauxioapi-0.1.5.dist-info/metadata.json
fauxioapi-0.1.5.dist-info/top_level.txt
