Metadata-Version: 2.0
Name: fauxioapi
Version: 0.1.5
Summary: A simple module reproducing limited I/O API functions
Home-page: https://github.com/jlbeidler/fauxioapi
Author-email: james.beidler@gmail.com
License: UNKNOWN
Platform: UNKNOWN
Requires-Python: >=3.5
Requires-Dist: netCDF4 (>=1.2.9)
Requires-Dist: numpy (>=1.16)
